README.rst
setup.py
RomanAlphabet/__init__.py
RomanAlphabet/romanalphabet.py
RomanAlphabet.egg-info/PKG-INFO
RomanAlphabet.egg-info/SOURCES.txt
RomanAlphabet.egg-info/dependency_links.txt
RomanAlphabet.egg-info/top_level.txt