Metadata-Version: 1.1
Name: RomanAlphabet
Version: 1.3
Summary: Numeral systems, binary, roman, integer
Home-page: https://github.com/RedXBeard/RomanNumbers
Author: Barbaros YILDIRIM
Author-email: barbarosaliyildirim@gmail.com
License: UNKNOWN
Download-URL: https://github.com/RedXBeard/RomanNumbers/tarball/1.3
Keywords: roman,romanalphabet,integer converter,integer to roman,roman to integer,binary,binary convertion
Platform: UNKNOWN
Classifier: Intended Audience :: Developers
Classifier: Operating System :: OS Independent
Classifier: Programming Language :: Python :: 2.7
Classifier: Natural Language :: English
Classifier: License :: OSI Approved :: GNU Library or Lesser General Public License (LGPL)
